leosdk/__init__.py
leosdk/leo.py
leosdk/aws/array.py
leosdk/aws/cfg.py
leosdk/aws/combiner.py
leosdk/aws/dynamodb.py
leosdk/aws/firehose.py
leosdk/aws/kinesis.py
leosdk/aws/leo_stream.py
leosdk/aws/massuploader.py
leosdk/aws/payload.py
leosdk/aws/s3.py
leosdk-0.0.5.dist-info/METADATA
leosdk-0.0.5.dist-info/RECORD
leosdk-0.0.5.dist-info/WHEEL
leosdk-0.0.5.dist-info/top_level.txt
