Metadata-Version: 2.1
Name: leosdk
Version: 0.0.5
Summary: Python SDK for the Leo Platform
Home-page: https://github.com/LeoPlatform/python
Author: Monty Charlton
Author-email: mcharlton@leoinsights.com
License: MIT
Platform: UNKNOWN
Classifier: Programming Language :: Python :: 3
Classifier: License :: OSI Approved :: MIT License
Classifier: Operating System :: OS Independent
